mpip/__init__.py
mpip/mpip.py
mpip-0.1.3.dist-info/METADATA
mpip-0.1.3.dist-info/WHEEL
mpip-0.1.3.dist-info/entry_points.txt
mpip-0.1.3.dist-info/top_level.txt
mpip-0.1.3.dist-info/RECORD
