Metadata-Version: 2.1
Name: mpip
Version: 0.1.3
Summary: mpip is a thin wrapper around pip which helps you manage your project requirements.
Home-page: https://github.com/jjorissen52/mpip
Author: John-Paul Jorissen
Author-email: jjorissen52@gmail.com
License: MIT
Keywords: python pip requirements requirements.txt project management
Platform: UNKNOWN
Requires-Dist: fire
Requires-Dist: rich
Requires-Dist: execution-pipeline
